{
  "version": false,
  "globalDependencies": {
    "bluebird": "registry:dt/bluebird#3.0.0+20160907110115",
    "config": "registry:dt/config#0.0.0+20160317120654",
    "cookie-parser": "registry:dt/cookie-parser#1.3.4+20160316155526",
    "errorhandler": "registry:dt/errorhandler#0.0.0+20160316155526",
    "express": "registry:dt/express#4.0.0+20160708185218",
    "express-serve-static-core": "registry:dt/express-serve-static-core#4.0.0+20160829034835",
    "express-session": "registry:dt/express-session#0.0.0+20160819134112",
    "google-apps-script/google-apps-script.base": "registry:dt/google-apps-script/google-apps-script.base#0.0.0+20160316171810",
    "google-apps-script/google-apps-script.calendar": "registry:dt/google-apps-script/google-apps-script.calendar#0.0.0+20160316171810",
    "google-apps-script/google-apps-script.language": "registry:dt/google-apps-script/google-apps-script.language#0.0.0+20160316171810",
    "google-apps-script/google-apps-script.types": "registry:dt/google-apps-script/google-apps-script.types#0.0.0+20160316171810",
    "isomorphic-fetch": "registry:dt/isomorphic-fetch#0.0.0+20160830175641",
    "knex": "registry:dt/knex#0.0.0+20160819212955",
    "lodash": "registry:dt/lodash#4.14.0+20160830145422",
    "mime": "registry:dt/mime#0.0.0+20160316155526",
    "node": "registry:dt/node#6.0.0+20160909174046",
    "passport": "registry:dt/passport#0.2.0+20160720063208",
    "passport-google-oauth": "registry:dt/passport-google-oauth#1.0.3+20160619021532",
    "react": "registry:dt/react#0.14.0+20160829191040",
    "react-bootstrap": "registry:dt/react-bootstrap#0.0.0+20160806072414",
    "react-dom": "registry:dt/react-dom#0.14.0+20160412154040",
    "react-router": "registry:dt/react-router#2.0.0+20160828232736",
    "react-router-redux": "registry:dt/react-router-redux#4.0.0+20160724070902",
    "react-router/history": "registry:dt/react-router/history#2.0.0+20160316155526",
    "redux": "registry:dt/redux#3.5.2+20160703092728",
    "sequelize": "registry:dt/sequelize#3.4.1+20160815132916",
    "serve-static": "registry:dt/serve-static#0.0.0+20160606155157",
    "validator": "registry:dt/validator#4.5.1+20160316155526",
    "webpack-isomorphic-tools": "github:Perlmint/private_typings/webpack-isomorphic-tools.d.ts"
  },
  "dependencies": {
    "body-parser": "registry:npm/body-parser#1.15.2+20160815132839",
    "react-redux": "registry:npm/react-redux#4.4.0+20160614222153",
    "redux-thunk": "registry:npm/redux-thunk#2.0.0+20160525185520"
  }
}
